av_tmp-8.1.999.dist-info/WHEEL
av_tmp-8.1.999.dist-info/LICENSE.txt
av_tmp-8.1.999.dist-info/AUTHORS.py
av_tmp-8.1.999.dist-info/RECORD
av_tmp-8.1.999.dist-info/AUTHORS.rst
av_tmp-8.1.999.dist-info/METADATA
av_tmp-8.1.999.dist-info/top_level.txt
av_tmp-8.1.999.dist-info/entry_points.txt
av/datasets.py
av/error.cpython-39-x86_64-linux-gnu.so
av/deprecation.py
av/bytesource.cpython-39-x86_64-linux-gnu.so
av/plane.cpython-39-x86_64-linux-gnu.so
av/buffer.cpython-39-x86_64-linux-gnu.so
av/__main__.py
av/option.cpython-39-x86_64-linux-gnu.so
av/enum.cpython-39-x86_64-linux-gnu.so
av/dictionary.cpython-39-x86_64-linux-gnu.so
av/__init__.py
av/packet.cpython-39-x86_64-linux-gnu.so
av/frame.cpython-39-x86_64-linux-gnu.so
av/stream.cpython-39-x86_64-linux-gnu.so
av/logging.cpython-39-x86_64-linux-gnu.so
av/descriptor.cpython-39-x86_64-linux-gnu.so
av/utils.cpython-39-x86_64-linux-gnu.so
av/_core.cpython-39-x86_64-linux-gnu.so
av/format.cpython-39-x86_64-linux-gnu.so
av/subtitles/subtitle.cpython-39-x86_64-linux-gnu.so
av/subtitles/codeccontext.cpython-39-x86_64-linux-gnu.so
av/subtitles/__init__.py
av/subtitles/stream.cpython-39-x86_64-linux-gnu.so
av/data/__init__.py
av/data/stream.cpython-39-x86_64-linux-gnu.so
av/codec/codec.cpython-39-x86_64-linux-gnu.so
av/codec/__init__.py
av/codec/context.cpython-39-x86_64-linux-gnu.so
av/video/reformatter.cpython-39-x86_64-linux-gnu.so
av/video/codeccontext.cpython-39-x86_64-linux-gnu.so
av/video/plane.cpython-39-x86_64-linux-gnu.so
av/video/__init__.py
av/video/frame.cpython-39-x86_64-linux-gnu.so
av/video/stream.cpython-39-x86_64-linux-gnu.so
av/video/format.cpython-39-x86_64-linux-gnu.so
av/container/input.cpython-39-x86_64-linux-gnu.so
av/container/streams.cpython-39-x86_64-linux-gnu.so
av/container/core.cpython-39-x86_64-linux-gnu.so
av/container/__init__.py
av/container/pyio.cpython-39-x86_64-linux-gnu.so
av/container/output.cpython-39-x86_64-linux-gnu.so
av/filter/filter.cpython-39-x86_64-linux-gnu.so
av/filter/graph.cpython-39-x86_64-linux-gnu.so
av/filter/pad.cpython-39-x86_64-linux-gnu.so
av/filter/link.cpython-39-x86_64-linux-gnu.so
av/filter/__init__.py
av/filter/context.cpython-39-x86_64-linux-gnu.so
av/sidedata/sidedata.cpython-39-x86_64-linux-gnu.so
