Metadata-Version: 2.1
Name: av-tmp
Version: 8.1.999
Summary: Pythonic bindings for FFmpeg's libraries.
Home-page: https://github.com/PyAV-Org/PyAV
Author: Mike Boers
Author-email: pyav@mikeboers.com
License: BSD
Project-URL: Bug Reports, https://github.com/PyAV-Org/PyAV/issues
Project-URL: Documentation, https://pyav.org/docs
Project-URL: Feedstock, https://github.com/conda-forge/av-feedstock
Project-URL: Download, https://pypi.org/project/av
Platform: UNKNOWN
Classifier: Development Status :: 5 - Production/Stable
Classifier: Intended Audience :: Developers
Classifier: License :: OSI Approved :: BSD License
Classifier: Natural Language :: English
Classifier: Operating System :: MacOS :: MacOS X
Classifier: Operating System :: POSIX
Classifier: Operating System :: Unix
Classifier: Operating System :: Microsoft :: Windows
Classifier: Programming Language :: Cython
Classifier: Programming Language :: Python :: 3.6
Classifier: Programming Language :: Python :: 3.7
Classifier: Programming Language :: Python :: 3.8
Classifier: Programming Language :: Python :: 3.9
Classifier: Programming Language :: Python :: 3.10
Classifier: Topic :: Software Development :: Libraries :: Python Modules
Classifier: Topic :: Multimedia :: Sound/Audio
Classifier: Topic :: Multimedia :: Sound/Audio :: Conversion
Classifier: Topic :: Multimedia :: Video
Classifier: Topic :: Multimedia :: Video :: Conversion
License-File: LICENSE.txt
License-File: AUTHORS.py
License-File: AUTHORS.rst
